hs_tasnet/__init__.py
hs_tasnet/hs_tasnet.py
hs_tasnet/trainer.py
hs_tasnet-0.2.29.dist-info/METADATA
hs_tasnet-0.2.29.dist-info/WHEEL
hs_tasnet-0.2.29.dist-info/licenses/LICENSE
hs_tasnet-0.2.29.dist-info/RECORD
