Metadata-Version: 2.4
Name: HS-TasNet
Version: 0.2.29
Summary: HS TasNet
Project-URL: Homepage, https://pypi.org/project/hs-tasnet/
Project-URL: Repository, https://github.com/lucidrains/hs-tasnet
Author-email: Phil Wang <lucidrains@gmail.com>
License: MIT License
License-File: LICENSE
Keywords: artificial intelligence,deep learning,music separation,real time
Classifier: Development Status :: 4 - Beta
Classifier: Intended Audience :: Developers
Classifier: License :: OSI Approved :: MIT License
Classifier: Programming Language :: Python :: 3.9
Classifier: Topic :: Scientific/Engineering :: Artificial Intelligence
Requires-Python: >=3.9
Requires-Dist: accelerate>=1.10.0
Requires-Dist: einops>=0.8.1
Requires-Dist: einx>=0.3.0
Requires-Dist: ema-pytorch
Requires-Dist: librosa
Requires-Dist: loguru
Requires-Dist: matplotlib
Requires-Dist: musdb
Requires-Dist: sounddevice
Requires-Dist: soundfile
Requires-Dist: torch>=2.8
Requires-Dist: torchaudio
Requires-Dist: torchcodec
Provides-Extra: test
Requires-Dist: pytest; extra == 'test'
